LICENSE
README.md
setup.py
cae/ArchFlowJavaWeb.py
cae/Run.py
cae/__init__.py
cae/db.json
cae/templates/assembler.txt
cae/templates/dependency_wrapper.txt
cae/templates/entity.txt
cae/templates/entityFactory.txt
cae/templates/entityImplementation.txt
cae/templates/implementation_cuc.txt
cae/templates/implementation_ruc.txt
cae/templates/implementation_suc.txt
cae/templates/pom-adapters.txt
cae/templates/pom-assemblers.txt
cae/templates/pom-core.txt
cae/templates/pom.txt
cae/templates/use_case.txt
cae/templates/use_case_cuc.txt
cae/templates/use_case_factory.txt
cae/templates/use_case_implementation.txt
cae/templates/use_case_input.txt
cae/templates/use_case_output.txt
cae/templates/use_case_ruc.txt
cae/templates/use_case_suc.txt
cae_cli.egg-info/PKG-INFO
cae_cli.egg-info/SOURCES.txt
cae_cli.egg-info/dependency_links.txt
cae_cli.egg-info/requires.txt
cae_cli.egg-info/top_level.txt